[
  {
    "title": "The Pulse: \u2018Tokenmaxxing\u2019 as a weird new trend - The Pragmatic Engineer",
    "link": "https://blog.pragmaticengineer.com/the-pulse-tokenmaxxing-as-a-weird-new-trend/",
    "description": "At Meta, Microsoft, Salesforce and other large companies, devs are purposefully burning tokens (and money!) to inflate their AI usage and hit AI usage metrics which they treat as targets.",
    "image": "",
    "datetimestamp": "2026-04-23T16:55:40",
    "source": "Pragmatic Engineer",
    "category": "Tech News"
  }
]